Workbook

Sheet Dashboard
B2: M/Y LIMITLESS — APA TRACKER
B4: Advance Provisioning Allowance — running reconciliation for the charter
B6: TRIP DETAILS | E6: APA SUMMARY
B7: Vessel | C7: M/Y Limitless | E7: APA SENT TO US | F7: 2400
B8: Charter / Guest | C8: Joel Freeland | E8: Additional top-ups received | F8: 0
B9: Captain | C9: Luigi | E9: Total APA available | F9: =F7+F8 -> 2400
B10: Trip dates | C10: 17-19/07 | E10: Less: total receipts entered | F10: =SUM(Expenses!D3:D202)+Provisions!$D$2+Diesel!$F$3 -> 5336.93
B11: Currency | C11: EUR (€) | E11: BALANCE REMAINING | F11: =F9-F10 -> -2936.93
E12: % of APA spent | F12: =IFERROR(F10/F9,0) -> 2.2237208
B14: SPEND BY CATEGORY | E14: DIESEL SUMMARY
B15: Category | C15: Total (€) | E15: Price per litre | F15: =Diesel!$C$2 -> 1.75
B16: Fuel / Diesel (from Diesel tab) | C16: =Diesel!$F$3 -> 3727.5 | E16: Total litres consumed | F16: =Diesel!$F$2 -> 2130
B17: Food & Provisions (from Provisions tab) | C17: =Provisions!$D$2 -> 579.72 | E17: Total diesel cost | F17: =Diesel!$F$3 -> 3727.5
B18: Drinks & Bar | C18: =SUMIF(Expenses!C$3:C$202,B18,Expenses!D$3:D$202) -> 0
B19: Dockage / Marina | C19: =SUMIF(Expenses!C$3:C$202,B19,Expenses!D$3:D$202) -> 1029.71
B20: Crew Tips | C20: =SUMIF(Expenses!C$3:C$202,B20,Expenses!D$3:D$202) -> 0
B21: Miscellaneous | C21: =SUMIF(Expenses!C$3:C$202,B21,Expenses!D$3:D$202) -> 0
B22: TOTAL | C22: =SUM(C16:C21) -> 5336.93
B24: Yellow cells are inputs. Enter each purchase on the Expenses tab — totals here update automatically.

Sheet Expenses
A1: EXPENSE LOG — M/Y Limitless APA
A2: Date | B2: Day | C2: Category | D2: Amount (€) | E2: Vendor / Description | F2: Paid by | G2: Receipt # | H2: Running balance (€) | I2: Notes
A3: 46220 | B3: =IFERROR(TEXT(A3,"ddd"),"") -> Fri | C3: Dockage / Marina | D3: 579.07 | E3: Marina Tramontana - Soller | F3: Ship card | H3: =IF(A3="","",Dashboard!$F$9-SUM($D$3:D3)) -> 1820.93
A4: 46221 | B4: =IF(A4="","",TEXT(A4,"ddd")) -> Sat | C4: Dockage / Marina | D4: 450.64 | E4: Marina Port Andratx - Andratx | F4: Ship card | H4: =IF(A4="","",Dashboard!$F$9-SUM($D$3:D4)) -> 1370.29
B5: =IF(A5="","",TEXT(A5,"ddd")) | H5: =IF(A5="","",Dashboard!$F$9-SUM($D$3:D5))
B6: =IF(A6="","",TEXT(A6,"ddd")) | H6: =IF(A6="","",Dashboard!$F$9-SUM($D$3:D6))
B7: =IF(A7="","",TEXT(A7,"ddd")) | H7: =IF(A7="","",Dashboard!$F$9-SUM($D$3:D7))
B8: =IF(A8="","",TEXT(A8,"ddd")) | H8: =IF(A8="","",Dashboard!$F$9-SUM($D$3:D8))
B9: =IF(A9="","",TEXT(A9,"ddd")) | H9: =IF(A9="","",Dashboard!$F$9-SUM($D$3:D9))
B10: =IF(A10="","",TEXT(A10,"ddd")) | H10: =IF(A10="","",Dashboard!$F$9-SUM($D$3:D10))
B11: =IF(A11="","",TEXT(A11,"ddd")) | H11: =IF(A11="","",Dashboard!$F$9-SUM($D$3:D11))
B12: =IF(A12="","",TEXT(A12,"ddd")) | H12: =IF(A12="","",Dashboard!$F$9-SUM($D$3:D12))
B13: =IF(A13="","",TEXT(A13,"ddd")) | H13: =IF(A13="","",Dashboard!$F$9-SUM($D$3:D13))
B14: =IF(A14="","",TEXT(A14,"ddd")) | H14: =IF(A14="","",Dashboard!$F$9-SUM($D$3:D14))
B15: =IF(A15="","",TEXT(A15,"ddd")) | H15: =IF(A15="","",Dashboard!$F$9-SUM($D$3:D15))
B16: =IF(A16="","",TEXT(A16,"ddd")) | H16: =IF(A16="","",Dashboard!$F$9-SUM($D$3:D16))
... B202: =IF(A202="","",TEXT(A202,"ddd")) | H202: =IF(A202="","",Dashboard!$F$9-SUM($D$3:D202))

Sheet Provisions
A1: PROVISIONS RECEIPTS — M/Y Limitless
B2: PROVISIONS GRAND TOTAL → | D2: =SUM(D4:D203) -> 579.72 | E2: flows to Dashboard → Food & Provisions
A3: Date | B3: Supplier / Vendor | C3: Items / Description | D3: Amount (€) | E3: Receipt # | F3: Notes
A4: 46219 | B4: Makro | C4: provisions | D4: 210.35
A5: 46220 | B5: carrefour | C5: provisions | D5: 225.28
A6: 46220 | B6: carrefour | C6: provisions | D6: 13.11
A7: 46221 | B7: supermercado frau | C7: provisions | D7: 27.33
A8: 46221 | B8: sa botiga | C8: provisions | D8: 20.55
A9: 46222 | B9: eroski | C9: provisions | D9: 83.1

Sheet Diesel
A1: DIESEL CONSUMPTION — M/Y Limitless
B2: Price per litre (€) | C2: 1.75 | E2: TOTAL DIESEL LITRES → | F2: =SUM(E6:E205) -> 2130
B3: Generator burn rate (L/hr) | C3: 6 | E3: TOTAL DIESEL COST → | F3: =SUM(F6:F205) -> 3727.5
A4: Generator burn rate converts generator hours to litres. Set your genset's actual rate above. Engine consumption is entered directly in litres.
A5: Date | B5: Engine litres | C5: Generator hrs | D5: Gen litres | E5: Total litres | F5: Cost (€) | G5: Notes
A6: 2026-07-20 | B6: 1986 | C6: 24 | D6: =IF(C6="","",C6*$C$3) -> 144 | E6: =IF(AND(B6="",D6=""),"",N(B6)+N(D6)) -> 2130 | F6: =IF(E6="","",E6*$C$2) -> 3727.5 | G6: EXAMPLE ROW — overwrite or delete
D7: =IF(C7="","",C7*$C$3) | E7: =IF(AND(B7="",D7=""),"",N(B7)+N(D7)) | F7: =IF(E7="","",E7*$C$2)
D8: =IF(C8="","",C8*$C$3) | E8: =IF(AND(B8="",D8=""),"",N(B8)+N(D8)) | F8: =IF(E8="","",E8*$C$2)
D9: =IF(C9="","",C9*$C$3) | E9: =IF(AND(B9="",D9=""),"",N(B9)+N(D9)) | F9: =IF(E9="","",E9*$C$2)
D10: =IF(C10="","",C10*$C$3) | E10: =IF(AND(B10="",D10=""),"",N(B10)+N(D10)) | F10: =IF(E10="","",E10*$C$2)
D11: =IF(C11="","",C11*$C$3) | E11: =IF(AND(B11="",D11=""),"",N(B11)+N(D11)) | F11: =IF(E11="","",E11*$C$2)
D12: =IF(C12="","",C12*$C$3) | E12: =IF(AND(B12="",D12=""),"",N(B12)+N(D12)) | F12: =IF(E12="","",E12*$C$2)
D13: =IF(C13="","",C13*$C$3) | E13: =IF(AND(B13="",D13=""),"",N(B13)+N(D13)) | F13: =IF(E13="","",E13*$C$2)
D14: =IF(C14="","",C14*$C$3) | E14: =IF(AND(B14="",D14=""),"",N(B14)+N(D14)) | F14: =IF(E14="","",E14*$C$2)
D15: =IF(C15="","",C15*$C$3) | E15: =IF(AND(B15="",D15=""),"",N(B15)+N(D15)) | F15: =IF(E15="","",E15*$C$2)
D16: =IF(C16="","",C16*$C$3) | E16: =IF(AND(B16="",D16=""),"",N(B16)+N(D16)) | F16: =IF(E16="","",E16*$C$2)
D17: =IF(C17="","",C17*$C$3) | E17: =IF(AND(B17="",D17=""),"",N(B17)+N(D17)) | F17: =IF(E17="","",E17*$C$2)
D18: =IF(C18="","",C18*$C$3) | E18: =IF(AND(B18="",D18=""),"",N(B18)+N(D18)) | F18: =IF(E18="","",E18*$C$2)
... D205: =IF(C205="","",C205*$C$3) | E205: =IF(AND(B205="",D205=""),"",N(B205)+N(D205)) | F205: =IF(E205="","",E205*$C$2)
